Metadata-Version: 2.1
Name: micromentor-django-pattern-library
Version: 0.0.1
Summary: A module for Django that allows to build pattern libraries for your projects, forked for MicroMentor.
Home-page: https://github.com/KennyMonster/django-pattern-library
License: BSD-3-Clause
Author: Ben Dickinson
Author-email: ben.dickinson@torchbox.com
Requires-Python: >=3.6,<4.0
Classifier: Development Status :: 4 - Beta
Classifier: Environment :: Web Environment
Classifier: Framework :: Django
Classifier: Framework :: Django :: 2.2
Classifier: Framework :: Django :: 3.0
Classifier: Framework :: Django :: 3.1
Classifier: Intended Audience :: Developers
Classifier: License :: OSI Approved :: BSD License
Classifier: Operating System :: OS Independent
Classifier: Programming Language :: Python
Classifier: Programming Language :: Python :: 3
Classifier: Programming Language :: Python :: 3.6
Classifier: Programming Language :: Python :: 3.7
Classifier: Programming Language :: Python :: 3.8
Classifier: Programming Language :: Python :: 3.9
Requires-Dist: Django (>=2.2,<4.0)
Requires-Dist: Markdown (>=3.1,<4.0)
Requires-Dist: PyYAML (>=5.1,<6.0)
Project-URL: Documentation, https://torchbox.github.io/django-pattern-library/
Project-URL: Repository, https://github.com/KennyMonster/django-pattern-library
